<annotation>
	<folder>JPEGImages</folder>
	<filename>001_jpg.rf.1e14d4cd330d97e6b451c10dc1a5d7fd.jpg</filename>
	<path>C:\Users\87018\Desktop\Vegetables_v3.v11i.voc\JPEGImages\001_jpg.rf.1e14d4cd330d97e6b451c10dc1a5d7fd.jpg</path>
	<source>
		<database>Unknown</database>
	</source>
	<size>
		<width>640</width>
		<height>640</height>
		<depth>3</depth>
	</size>
	<segmented>0</segmented>
	<object>
		<name>tomato</name>
		<pose>Unspecified</pose>
		<truncated>1</truncated>
		<difficult>0</difficult>
		<bndbox>
			<xmin>29</xmin>
			<ymin>1</ymin>
			<xmax>283</xmax>
			<ymax>223</ymax>
		</bndbox>
	</object>
	<object>
		<name>tomato</name>
		<pose>Unspecified</pose>
		<truncated>1</truncated>
		<difficult>0</difficult>
		<bndbox>
			<xmin>359</xmin>
			<ymin>1</ymin>
			<xmax>481</xmax>
			<ymax>238</ymax>
		</bndbox>
	</object>
	<object>
		<name>tomato</name>
		<pose>Unspecified</pose>
		<truncated>1</truncated>
		<difficult>0</difficult>
		<bndbox>
			<xmin>442</xmin>
			<ymin>2</ymin>
			<xmax>640</xmax>
			<ymax>244</ymax>
		</bndbox>
	</object>
	<object>
		<name>tomato</name>
		<pose>Unspecified</pose>
		<truncated>1</truncated>
		<difficult>0</difficult>
		<bndbox>
			<xmin>48</xmin>
			<ymin>435</ymin>
			<xmax>286</xmax>
			<ymax>640</ymax>
		</bndbox>
	</object>
	<object>
		<name>tomato</name>
		<pose>Unspecified</pose>
		<truncated>1</truncated>
		<difficult>0</difficult>
		<bndbox>
			<xmin>394</xmin>
			<ymin>486</ymin>
			<xmax>640</xmax>
			<ymax>640</ymax>
		</bndbox>
	</object>
</annotation>
