<annotation>
	<folder></folder>
	<filename>Image_23_jpg.rf.7bde8280ae48ae6bff1ee8a3571e5be6.jpg</filename>
	<path>Image_23_jpg.rf.7bde8280ae48ae6bff1ee8a3571e5be6.jpg</path>
	<source>
		<database>roboflow.com</database>
	</source>
	<size>
		<width>640</width>
		<height>640</height>
		<depth>3</depth>
	</size>
	<segmented>0</segmented>
	<object>
		<name>cucumber</name>
		<pose>Unspecified</pose>
		<truncated>0</truncated>
		<difficult>0</difficult>
		<occluded>0</occluded>
		<bndbox>
			<xmin>1</xmin>
			<xmax>321</xmax>
			<ymin>1</ymin>
			<ymax>301</ymax>
		</bndbox>
	</object>
	<object>
		<name>cucumber</name>
		<pose>Unspecified</pose>
		<truncated>0</truncated>
		<difficult>0</difficult>
		<occluded>0</occluded>
		<bndbox>
			<xmin>3</xmin>
			<xmax>321</xmax>
			<ymin>1</ymin>
			<ymax>301</ymax>
		</bndbox>
	</object>
	<object>
		<name>eggplant</name>
		<pose>Unspecified</pose>
		<truncated>0</truncated>
		<difficult>0</difficult>
		<occluded>0</occluded>
		<bndbox>
			<xmin>321</xmin>
			<xmax>395</xmax>
			<ymin>167</ymin>
			<ymax>253</ymax>
		</bndbox>
	</object>
	<object>
		<name>onion</name>
		<pose>Unspecified</pose>
		<truncated>0</truncated>
		<difficult>0</difficult>
		<occluded>0</occluded>
		<bndbox>
			<xmin>391</xmin>
			<xmax>510</xmax>
			<ymin>94</ymin>
			<ymax>280</ymax>
		</bndbox>
	</object>
	<object>
		<name>eggplant</name>
		<pose>Unspecified</pose>
		<truncated>0</truncated>
		<difficult>0</difficult>
		<occluded>0</occluded>
		<bndbox>
			<xmin>496</xmin>
			<xmax>536</xmax>
			<ymin>152</ymin>
			<ymax>257</ymax>
		</bndbox>
	</object>
	<object>
		<name>onion</name>
		<pose>Unspecified</pose>
		<truncated>0</truncated>
		<difficult>0</difficult>
		<occluded>0</occluded>
		<bndbox>
			<xmin>520</xmin>
			<xmax>605</xmax>
			<ymin>160</ymin>
			<ymax>278</ymax>
		</bndbox>
	</object>
	<object>
		<name>carrot</name>
		<pose>Unspecified</pose>
		<truncated>0</truncated>
		<difficult>0</difficult>
		<occluded>0</occluded>
		<bndbox>
			<xmin>555</xmin>
			<xmax>641</xmax>
			<ymin>218</ymin>
			<ymax>301</ymax>
		</bndbox>
	</object>
	<object>
		<name>zucchini</name>
		<pose>Unspecified</pose>
		<truncated>0</truncated>
		<difficult>0</difficult>
		<occluded>0</occluded>
		<bndbox>
			<xmin>321</xmin>
			<xmax>472</xmax>
			<ymin>301</ymin>
			<ymax>641</ymax>
		</bndbox>
	</object>
</annotation>
