<annotation>
	<folder></folder>
	<filename>IMG_7580_jpg.rf.f96258b9de26761509f1c96ced28db5e.jpg</filename>
	<path>IMG_7580_jpg.rf.f96258b9de26761509f1c96ced28db5e.jpg</path>
	<source>
		<database>roboflow.com</database>
	</source>
	<size>
		<width>640</width>
		<height>640</height>
		<depth>3</depth>
	</size>
	<segmented>0</segmented>
	<object>
		<name>tomato</name>
		<pose>Unspecified</pose>
		<truncated>0</truncated>
		<difficult>0</difficult>
		<occluded>0</occluded>
		<bndbox>
			<xmin>135</xmin>
			<xmax>290</xmax>
			<ymin>256</ymin>
			<ymax>576</ymax>
		</bndbox>
		<polygon>
			<x1>148.62</x1>
			<y1>527.969</y1>
			<x2>262.979</x2>
			<y2>574.514</y2>
			<x3>289.451</x3>
			<y3>471.552</y3>
			<x4>260.106</x4>
			<y4>254.674</y4>
			<x5>133.796</x5>
			<y5>417.955</y5>
			<x6>148.62</x6>
			<y6>527.969</y6>
		</polygon>
	</object>
	<object>
		<name>carrot</name>
		<pose>Unspecified</pose>
		<truncated>0</truncated>
		<difficult>0</difficult>
		<occluded>0</occluded>
		<bndbox>
			<xmin>293</xmin>
			<xmax>415</xmax>
			<ymin>284</ymin>
			<ymax>354</ymax>
		</bndbox>
		<polygon>
			<x1>414.399</x1>
			<y1>282.553</y1>
			<x2>291.569</x2>
			<y2>319.224</y2>
			<x3>310.629</x3>
			<y3>353.075</y3>
			<x4>414.399</x4>
			<y4>282.553</y4>
		</polygon>
	</object>
	<object>
		<name>carrot</name>
		<pose>Unspecified</pose>
		<truncated>0</truncated>
		<difficult>0</difficult>
		<occluded>0</occluded>
		<bndbox>
			<xmin>336</xmin>
			<xmax>409</xmax>
			<ymin>304</ymin>
			<ymax>416</ymax>
		</bndbox>
		<polygon>
			<x1>407.725</x1>
			<y1>303.351</y1>
			<x2>338.16</x2>
			<y2>368.59</y2>
			<x3>334.983</x3>
			<y3>415.134</y3>
			<x4>358.278</x4>
			<y4>409.493</y4>
			<x5>407.725</x5>
			<y5>303.351</y5>
		</polygon>
	</object>
	<object>
		<name>bell_pepper</name>
		<pose>Unspecified</pose>
		<truncated>0</truncated>
		<difficult>0</difficult>
		<occluded>0</occluded>
		<bndbox>
			<xmin>324</xmin>
			<xmax>426</xmax>
			<ymin>175</ymin>
			<ymax>280</ymax>
		</bndbox>
	</object>
</annotation>
